puco/__init__.py
puco/connection.py
puco-0.1.2.dist-info/LICENSE
puco-0.1.2.dist-info/METADATA
puco-0.1.2.dist-info/WHEEL
puco-0.1.2.dist-info/top_level.txt
puco-0.1.2.dist-info/RECORD
